{
  "entityType" : "NOTIFICATION_RULE",
  "entity" : {
    "additionalConfig" : {
      "description" : "Send notification to tenant admins when any alarm is updated or cleared"
    },
    "enabled" : true,
    "externalId" : null,
    "id" : {
      "entityType" : "NOTIFICATION_RULE",
      "id" : "8071a310-bad7-11ee-aa1f-c7b4d28064dd"
    },
    "name" : "Alarm update",
    "recipientsConfig" : {
      "escalationTable" : {
        "0" : [ "80698cc0-bad7-11ee-aa1f-c7b4d28064dd", "76f372d0-bc91-11ee-9e6f-1d0e98d6d74a" ]
      },
      "triggerType" : "ALARM"
    },
    "templateId" : {
      "entityType" : "NOTIFICATION_TEMPLATE",
      "id" : "806fce50-bad7-11ee-aa1f-c7b4d28064dd"
    },
    "triggerConfig" : {
      "triggerType" : "ALARM",
      "alarmSeverities" : null,
      "alarmTypes" : null,
      "clearRule" : null,
      "notifyOn" : [ "ACKNOWLEDGED", "SEVERITY_CHANGED", "CLEARED" ],
      "triggerType" : "ALARM"
    },
    "triggerType" : "ALARM"
  },
  "relations" : [ ],
  "attributes" : {
    "SERVER_SCOPE" : [ ]
  }
}